django33_table/__init__.py
django33_table/columns/__init__.py
django33_table/columns/base.py
django33_table/columns/booleancolumn.py
django33_table/columns/checkboxcolumn.py
django33_table/columns/datecolumn.py
django33_table/columns/datetimecolumn.py
django33_table/columns/emailcolumn.py
django33_table/columns/filecolumn.py
django33_table/columns/jsoncolumn.py
django33_table/columns/linkcolumn.py
django33_table/columns/manytomanycolumn.py
django33_table/columns/templatecolumn.py
django33_table/columns/timecolumn.py
django33_table/columns/urlcolumn.py
django33_table/config.py
django33_table/data.py
django33_table/export/__init__.py
django33_table/export/export.py
django33_table/export/views.py
django33_table/locale/cs/LC_MESSAGES/django.mo
django33_table/locale/cs/LC_MESSAGES/django.po
django33_table/locale/de/LC_MESSAGES/django.mo
django33_table/locale/de/LC_MESSAGES/django.po
django33_table/locale/el/LC_MESSAGES/django.mo
django33_table/locale/el/LC_MESSAGES/django.po
django33_table/locale/en/LC_MESSAGES/django.mo
django33_table/locale/en/LC_MESSAGES/django.po
django33_table/locale/es/LC_MESSAGES/django.mo
django33_table/locale/es/LC_MESSAGES/django.po
django33_table/locale/fa/LC_MESSAGES/django.mo
django33_table/locale/fa/LC_MESSAGES/django.po
django33_table/locale/fr/LC_MESSAGES/django.mo
django33_table/locale/fr/LC_MESSAGES/django.po
django33_table/locale/hu/LC_MESSAGES/django.mo
django33_table/locale/hu/LC_MESSAGES/django.po
django33_table/locale/it/LC_MESSAGES/django.mo
django33_table/locale/it/LC_MESSAGES/django.po
django33_table/locale/lt/LC_MESSAGES/django.mo
django33_table/locale/lt/LC_MESSAGES/django.po
django33_table/locale/nb/LC_MESSAGES/django.mo
django33_table/locale/nb/LC_MESSAGES/django.po
django33_table/locale/nl/LC_MESSAGES/django.mo
django33_table/locale/nl/LC_MESSAGES/django.po
django33_table/locale/pl/LC_MESSAGES/django.mo
django33_table/locale/pl/LC_MESSAGES/django.po
django33_table/locale/pt_BR/LC_MESSAGES/django.mo
django33_table-0.1.0.dist-info/METADATA
django33_table-0.1.0.dist-info/WHEEL
django33_table-0.1.0.dist-info/RECORD
