Metadata-Version: 2.1
Name: django33-table
Version: 0.1.0
Summary: 
Author: zhangdapeng
Author-email: 1156956636@qq.com
Requires-Python: >=3.12,<4.0
Classifier: Programming Language :: Python :: 3
Classifier: Programming Language :: Python :: 3.12
Classifier: Programming Language :: Python :: 3.13
